pytarantula.py
pytarantula-0.1.2.dist-info/METADATA
pytarantula-0.1.2.dist-info/WHEEL
pytarantula-0.1.2.dist-info/RECORD
