Metadata-Version: 2.1
Name: pytarantula
Version: 0.1.2
Summary: Python client for tarantula service.
Author: pierre steen
Author-email: pierre@84a.dev
Requires-Python: >=3.11,<4.0
Classifier: Programming Language :: Python :: 3
Classifier: Programming Language :: Python :: 3.11
